treed/__init__.py
treed/__main__.py
treed/treed.py
treed-2.1.0.dist-info/LICENSE.txt
treed-2.1.0.dist-info/METADATA
treed-2.1.0.dist-info/WHEEL
treed-2.1.0.dist-info/top_level.txt
treed-2.1.0.dist-info/RECORD
