Metadata-Version: 2.1
Name: treed
Version: 2.1.0
Summary: 3D Visualization of Branch-and-Cut Trees using PySCIPOpt
Home-page: https://github.com/mattmilten/TreeD
Author: Matthias Miltenberger
Author-email: matthias.miltenberger@gmail.com
License: UNKNOWN
Platform: UNKNOWN
Classifier: Programming Language :: Python :: 3
Classifier: License :: OSI Approved :: MIT License
Classifier: Operating System :: OS Independent
Requires-Python: >=3.6
License-File: LICENSE.txt
Requires-Dist: pyscipopt
Requires-Dist: scikit-learn
Requires-Dist: pandas
Requires-Dist: plotly
Requires-Dist: networkx
Requires-Dist: numpy
